vlm_dataset_captioner/__init__.py
vlm_dataset_captioner/vlm_caption.py
vlm_dataset_captioner/vlm_caption_cli.py
vlm_dataset_captioner-0.0.3.dist-info/METADATA
vlm_dataset_captioner-0.0.3.dist-info/WHEEL
vlm_dataset_captioner-0.0.3.dist-info/entry_points.txt
vlm_dataset_captioner-0.0.3.dist-info/RECORD
