Metadata-Version: 2.4
Name: vlm-dataset-captioner
Version: 0.0.3
Summary: Uses a VLM to caption images from a dataset.
Author: Alex Senden
Maintainer: Alex Senden
License: MIT
Keywords: computer-vision,image-captioning,machine-learning,vision-language-model
Classifier: Development Status :: 3 - Alpha
Classifier: Intended Audience :: Developers
Classifier: Programming Language :: Python :: 3
Classifier: Programming Language :: Python :: 3.8
Classifier: Programming Language :: Python :: 3.9
Classifier: Programming Language :: Python :: 3.10
Classifier: Programming Language :: Python :: 3.11
Classifier: Topic :: Scientific/Engineering :: Image Processing
Requires-Python: >=3.8
Requires-Dist: accelerate
Requires-Dist: huggingface-hub
Requires-Dist: qwen-vl-utils
Requires-Dist: torch
Requires-Dist: torchvision
Requires-Dist: transformers
